[{"line":2,"elements":[{"start_timestamp":"2023-05-22T13:11:34.043Z","before":[{"result":{"duration":1866981700,"status":"passed"},"match":{"location":"com.qa.utils.Setup.setWebDriver()"}}],"line":4,"name":"Login","description":"","id":"login;login","after":[{"result":{"duration":118744200,"status":"passed"},"match":{"location":"com.qa.utils.TearDown.quitDriver(io.cucumber.java.Scenario)"}}],"type":"scenario","keyword":"Scenario","steps":[{"result":{"duration":3714561300,"status":"passed"},"line":5,"name":"Je me connecte sur l'application","match":{"location":"com.qa.step_definitions.LoginStepDefs.jeMeConnecteSurLApplication()"},"keyword":"Given "},{"result":{"duration":114147800,"status":"passed"},"line":6,"name":"Je saisis le username","match":{"location":"com.qa.step_definitions.LoginStepDefs.jeSaisisLeUsername()"},"keyword":"When "},{"result":{"duration":115251900,"status":"passed"},"line":7,"name":"Je saisis le mot de passe","match":{"location":"com.qa.step_definitions.LoginStepDefs.jeSaisisLeMotDePasse()"},"keyword":"And "},{"result":{"duration":765431000,"status":"passed"},"line":8,"name":"Je clique sur le bouton Login","match":{"location":"com.qa.step_definitions.LoginStepDefs.jeCliqueSurLeBoutonLogin()"},"keyword":"And "}],"tags":[{"name":"@login"}]}],"name":"Login","description":"","id":"login","keyword":"Feature","uri":"file:src/spec/feature/login.feature","tags":[{"name":"@login","type":"Tag","location":{"line":1,"column":1}}]}]